{
  "kind": "singleType",
  "collectionName": "page-ultimo-recurso",
  "info": {
    "name": "Página Ultimo Recurso",
    "description": ""
  },
  "options": {
    "increments": true,
    "timestamps": true,
    "draftAndPublish": true
  },
  "pluginOptions": {
    "i18n": {
      "localized": true
    }
  },
  "attributes": {
    "title": {
      "type": "string",
      "pluginOptions": {
        "i18n": {
          "localized": true
        }
      }
    },
    "HomeBanner": {
      "type": "component",
      "repeatable": false,
      "pluginOptions": {
        "i18n": {
          "localized": true
        }
      },
      "component": "universal-blocks.fullscreen-banner"
    },
    "VideoDocumentario": {
      "type": "component",
      "repeatable": false,
      "pluginOptions": {
        "i18n": {
          "localized": true
        }
      },
      "component": "universal-blocks.video-block"
    },
    "StripText": {
      "type": "component",
      "repeatable": false,
      "pluginOptions": {
        "i18n": {
          "localized": true
        }
      },
      "component": "universal-blocks.strip-text"
    },
    "QuoteConstituicao": {
      "type": "component",
      "repeatable": false,
      "pluginOptions": {
        "i18n": {
          "localized": true
        }
      },
      "component": "universal-blocks.strip-text-link"
    },
    "FourImagesBlock": {
      "type": "component",
      "repeatable": false,
      "pluginOptions": {
        "i18n": {
          "localized": true
        }
      },
      "component": "universal-blocks.four-images-block"
    },
    "GotaDaAgua": {
      "type": "component",
      "repeatable": false,
      "pluginOptions": {
        "i18n": {
          "localized": true
        }
      },
      "component": "universal-blocks.text-banner"
    },
    "AlessandreVieira": {
      "type": "component",
      "repeatable": false,
      "pluginOptions": {
        "i18n": {
          "localized": true
        }
      },
      "component": "universal-blocks.simple-quote"
    },
    "SaidaBolsonaro": {
      "type": "component",
      "repeatable": false,
      "pluginOptions": {
        "i18n": {
          "localized": true
        }
      },
      "component": "universal-blocks.simple-quote"
    },
    "ArrozComFuzil": {
      "type": "component",
      "repeatable": false,
      "pluginOptions": {
        "i18n": {
          "localized": true
        }
      },
      "component": "universal-blocks.image-text"
    },
    "ArrozComFuzil2": {
      "type": "component",
      "repeatable": false,
      "pluginOptions": {
        "i18n": {
          "localized": true
        }
      },
      "component": "universal-blocks.image-desc"
    },
    "Anamatra": {
      "type": "component",
      "repeatable": false,
      "pluginOptions": {
        "i18n": {
          "localized": true
        }
      },
      "component": "universal-blocks.simple-quote"
    },
    "ArtigoMatilde": {
      "type": "component",
      "repeatable": false,
      "pluginOptions": {
        "i18n": {
          "localized": true
        }
      },
      "component": "universal-blocks.image-text"
    },
    "CarlosAyres": {
      "type": "component",
      "repeatable": true,
      "pluginOptions": {
        "i18n": {
          "localized": true
        }
      },
      "component": "universal-blocks.simple-quote"
    },
    "ContagemProgressiva": {
      "type": "component",
      "repeatable": false,
      "pluginOptions": {
        "i18n": {
          "localized": true
        }
      },
      "component": "universal-blocks.contagem-progressiva"
    },
    "FotoPB": {
      "type": "component",
      "repeatable": false,
      "pluginOptions": {
        "i18n": {
          "localized": true
        }
      },
      "component": "universal-blocks.image-text"
    },
    "Credits": {
      "pluginOptions": {
        "i18n": {
          "localized": true
        }
      },
      "type": "richtext"
    },
    "FooterLinks": {
      "type": "component",
      "repeatable": true,
      "pluginOptions": {
        "i18n": {
          "localized": true
        }
      },
      "component": "universal-blocks.link"
    }
  }
}
